<pkgref spec="1.12" uuid="FCBE98B8-6273-449D-9ECE-FC188869AF87"><config><identifier>ch.entropy.php.mcrypt</identifier><version>5.2.9</version><description></description><post-install type="none"/><requireAuthorization/><installTo mod="true">/usr/local/php5/</installTo><flags/><packageStore type="internal"></packageStore><mod>parent</mod><mod>installSizeKB</mod><mod>requireAuthorization</mod><mod>postInstall</mod><mod>relocatable</mod><mod>version</mod><mod>installTo.path</mod><mod>extraFiles</mod><mod>identifier</mod><mod>installTo</mod></config><extra><packagePath>/private/tmp/build-entropy-php-pkgdst/entropy-php-extension-mcrypt.pkg</packagePath><title>entropy-php-extension-mcrypt</title></extra><extra-files/></pkgref>